{
  "offers": [
    {
      "title": "Pro",
      "unit": "mo",
      "price": 1300,
      "items": [
        "20 users included",
        "10 GB of storage",
        "Priority email support",
        "Help center access"
      ],
      "textButton": "Sign up for free"
    },
    {
      "title": "Enterprise",
      "unit": "mo",
      "price": 1800,
      "items": [
        "30 users included",
        "15 GB of storage",
        "Phone and email support",
        "Help center access"
      ],
      "textButton": "Sign up for free"
    }
  ]
}
